pyMelt/__init__.py
pyMelt/chemistry.py
pyMelt/core.py
pyMelt/geosettings.py
pyMelt/lithology_classes.py
pyMelt/mantle_class.py
pyMelt/meltingcolumn_classes.py
pyMelt/phaseDiagramTools.py
pyMelt/lithologies/__init__.py
pyMelt/lithologies/ball.py
pyMelt/lithologies/katz.py
pyMelt/lithologies/matthews.py
pyMelt/lithologies/mckenzie.py
pyMelt/lithologies/pertermann.py
pyMelt/lithologies/shorttle.py
pyMelt/phaseDiagrams/melts_klb1.p
pyMelt/phaseDiagrams/thermocalc_kg1.p
pyMelt/phaseDiagrams/thermocalc_klb1.p
pyMelt/phaseDiagrams/build/Import_pmelts_klb1.ipynb
pyMelt/phaseDiagrams/build/Import_thermocalc_kg1.ipynb
pyMelt/phaseDiagrams/build/Import_thermocalc_klb1.ipynb
pyMelt/phaseDiagrams/build/kg1_thermocalc_grid.csv
pyMelt/phaseDiagrams/build/klb1_pmelts_grid.csv
pyMelt/phaseDiagrams/build/klb1_thermocalc_grid.csv
tests/__init__.py
tests/test_chemistry.py
tests/test_geosettings.py
tests/test_hydrousLithology.py
tests/test_lithologies.py
tests/test_mantleClass.py
pyMelt-2.3.dist-info/LICENSE
pyMelt-2.3.dist-info/METADATA
pyMelt-2.3.dist-info/WHEEL
pyMelt-2.3.dist-info/top_level.txt
pyMelt-2.3.dist-info/RECORD
