Metadata-Version: 2.1
Name: pyMelt
Version: 2.3
Summary: A python library for calculating the melting behaviour of Earth's mantle.
Home-page: https://github.com/simonwmatthews/pyMelt
Author: Simon Matthews, Kevin Wong, Matthew Gleeson
Author-email: simonwmatthews@gmail.com
Classifier: Programming Language :: Python :: 3
Classifier: License :: OSI Approved :: MIT License
Classifier: Operating System :: OS Independent
Requires-Python: >=3.6
License-File: LICENSE
Requires-Dist: pandas >=1.3.5
Requires-Dist: numpy >=1.21.5
Requires-Dist: matplotlib >=3.5.1
Requires-Dist: scipy >=1.7.3
